setup.py
morbo/__init__.py
morbo/connection.py
morbo/cursor.py
morbo/model.py
morbo/registry.py
morbo/relationships.py
morbo/validators.py
morbo/version.py
morbo.egg-info/PKG-INFO
morbo.egg-info/SOURCES.txt
morbo.egg-info/dependency_links.txt
morbo.egg-info/requires.txt
morbo.egg-info/top_level.txt