Metadata-Version: 1.0
Name: morbo
Version: 1.1.4
Summary: A MongoDB object mapper for puny humans.
Home-page: https://github.com/elishacook/morbo
Author: Elisha Cook
Author-email: elisha@elishacook.com
License: UNKNOWN
Platform: UNKNOWN
